[
    {
        "id": 9,
        "name": "Banjir Teluk Betung Selatan",
        "address": "Genangan sekitar akses Pesawahan dan Teluk Betung Selatan",
        "district": "Teluk Betung Selatan",
        "subdistrict": "Pesawahan",
        "source_type": "admin_input",
        "source_reference": "Dataset simulasi pengembangan SIGAP Banjir; lokasi area diverifikasi melalui peta publik OpenStreetMap/Nominatim, kejadian banjir merupakan skenario uji aplikasi.",
        "is_verified": false,
        "data_status": "simulasi",
        "longitude": 105.2607,
        "latitude": -5.4478,
        "dataset": "flood_events"
    },
    {
        "id": 10,
        "name": "Genangan Way Halim",
        "address": "Genangan permukiman Way Halim Permai",
        "district": "Way Halim",
        "subdistrict": "Way Halim Permai",
        "source_type": "admin_input",
        "source_reference": "Dataset simulasi pengembangan SIGAP Banjir; lokasi area diverifikasi melalui peta publik OpenStreetMap/Nominatim, kejadian banjir merupakan skenario uji aplikasi.",
        "is_verified": false,
        "data_status": "simulasi",
        "longitude": 105.2869,
        "latitude": -5.3867,
        "dataset": "flood_events"
    },
    {
        "id": 11,
        "name": "Banjir Korpri Sukarame",
        "address": "Genangan Korpri Raya Sukarame",
        "district": "Sukarame",
        "subdistrict": "Korpri Raya",
        "source_type": "admin_input",
        "source_reference": "Dataset simulasi pengembangan SIGAP Banjir; lokasi area diverifikasi melalui peta publik OpenStreetMap/Nominatim, kejadian banjir merupakan skenario uji aplikasi.",
        "is_verified": false,
        "data_status": "simulasi",
        "longitude": 105.3045,
        "latitude": -5.3832,
        "dataset": "flood_events"
    },
    {
        "id": 12,
        "name": "Genangan Panjang Utara",
        "address": "Genangan akses logistik Panjang Utara",
        "district": "Panjang",
        "subdistrict": "Panjang Utara",
        "source_type": "admin_input",
        "source_reference": "Dataset simulasi pengembangan SIGAP Banjir; lokasi area diverifikasi melalui peta publik OpenStreetMap/Nominatim, kejadian banjir merupakan skenario uji aplikasi.",
        "is_verified": false,
        "data_status": "simulasi",
        "longitude": 105.3278,
        "latitude": -5.4658,
        "dataset": "flood_events"
    },
    {
        "id": 13,
        "name": "Banjir Rajabasa Nunyai",
        "address": "Genangan permukiman Rajabasa Nunyai",
        "district": "Rajabasa",
        "subdistrict": "Rajabasa Nunyai",
        "source_type": "admin_input",
        "source_reference": "Dataset simulasi pengembangan SIGAP Banjir; lokasi area diverifikasi melalui peta publik OpenStreetMap/Nominatim, kejadian banjir merupakan skenario uji aplikasi.",
        "is_verified": false,
        "data_status": "simulasi",
        "longitude": 105.2294,
        "latitude": -5.3716,
        "dataset": "flood_events"
    },
    {
        "id": 14,
        "name": "Genangan Kedamaian",
        "address": "Genangan lokal pada koridor Kedamaian",
        "district": "Kedamaian",
        "subdistrict": "Kedamaian",
        "source_type": "admin_input",
        "source_reference": "Dataset simulasi pengembangan SIGAP Banjir; lokasi area diverifikasi melalui peta publik OpenStreetMap/Nominatim, kejadian banjir merupakan skenario uji aplikasi.",
        "is_verified": false,
        "data_status": "simulasi",
        "longitude": 105.2828,
        "latitude": -5.4082,
        "dataset": "flood_events"
    },
    {
        "id": 15,
        "name": "Banjir Bumi Waras",
        "address": "Genangan rendah sekitar Bumi Waras",
        "district": "Bumi Waras",
        "subdistrict": "Bumi Waras",
        "source_type": "admin_input",
        "source_reference": "Dataset simulasi pengembangan SIGAP Banjir; lokasi area diverifikasi melalui peta publik OpenStreetMap/Nominatim, kejadian banjir merupakan skenario uji aplikasi.",
        "is_verified": false,
        "data_status": "simulasi",
        "longitude": 105.2702,
        "latitude": -5.4352,
        "dataset": "flood_events"
    },
    {
        "id": 16,
        "name": "Genangan Enggal",
        "address": "Genangan ringan pusat kota Enggal",
        "district": "Enggal",
        "subdistrict": "Enggal",
        "source_type": "admin_input",
        "source_reference": "Dataset simulasi pengembangan SIGAP Banjir; lokasi area diverifikasi melalui peta publik OpenStreetMap/Nominatim, kejadian banjir merupakan skenario uji aplikasi.",
        "is_verified": false,
        "data_status": "simulasi",
        "longitude": 105.2639,
        "latitude": -5.4206,
        "dataset": "flood_events"
    },
    {
        "id": 13,
        "name": "Rawan Banjir Way Halim",
        "address": "Koridor permukiman Way Halim Permai",
        "district": "Way Halim",
        "subdistrict": "Way Halim Permai",
        "source_type": "admin_input",
        "source_reference": "Dataset simulasi pengembangan SIGAP Banjir; lokasi area diverifikasi melalui peta publik OpenStreetMap/Nominatim, tingkat risiko merupakan skenario uji aplikasi.",
        "is_verified": false,
        "data_status": "simulasi",
        "longitude": 105.2886,
        "latitude": -5.3897,
        "dataset": "flood_risk_points"
    },
    {
        "id": 14,
        "name": "Rawan Banjir Teluk Betung Selatan",
        "address": "Sekitar Pesawahan dan akses pesisir",
        "district": "Teluk Betung Selatan",
        "subdistrict": "Pesawahan",
        "source_type": "admin_input",
        "source_reference": "Dataset simulasi pengembangan SIGAP Banjir; lokasi area diverifikasi melalui peta publik OpenStreetMap/Nominatim, tingkat risiko merupakan skenario uji aplikasi.",
        "is_verified": false,
        "data_status": "simulasi",
        "longitude": 105.2608,
        "latitude": -5.4469,
        "dataset": "flood_risk_points"
    },
    {
        "id": 15,
        "name": "Rawan Banjir Panjang Utara",
        "address": "Koridor akses Pelabuhan Panjang",
        "district": "Panjang",
        "subdistrict": "Panjang Utara",
        "source_type": "admin_input",
        "source_reference": "Dataset simulasi pengembangan SIGAP Banjir; lokasi area diverifikasi melalui peta publik OpenStreetMap/Nominatim, tingkat risiko merupakan skenario uji aplikasi.",
        "is_verified": false,
        "data_status": "simulasi",
        "longitude": 105.3284,
        "latitude": -5.4661,
        "dataset": "flood_risk_points"
    },
    {
        "id": 16,
        "name": "Rawan Banjir Rajabasa Nunyai",
        "address": "Permukiman sekitar Rajabasa Nunyai",
        "district": "Rajabasa",
        "subdistrict": "Rajabasa Nunyai",
        "source_type": "admin_input",
        "source_reference": "Dataset simulasi pengembangan SIGAP Banjir; lokasi area diverifikasi melalui peta publik OpenStreetMap/Nominatim, tingkat risiko merupakan skenario uji aplikasi.",
        "is_verified": false,
        "data_status": "simulasi",
        "longitude": 105.2302,
        "latitude": -5.3722,
        "dataset": "flood_risk_points"
    },
    {
        "id": 17,
        "name": "Rawan Banjir Korpri Sukarame",
        "address": "Area Korpri Raya Sukarame",
        "district": "Sukarame",
        "subdistrict": "Korpri Raya",
        "source_type": "admin_input",
        "source_reference": "Dataset simulasi pengembangan SIGAP Banjir; lokasi area diverifikasi melalui peta publik OpenStreetMap/Nominatim, tingkat risiko merupakan skenario uji aplikasi.",
        "is_verified": false,
        "data_status": "simulasi",
        "longitude": 105.3052,
        "latitude": -5.3838,
        "dataset": "flood_risk_points"
    },
    {
        "id": 18,
        "name": "Rawan Banjir Kedamaian",
        "address": "Koridor Kedamaian dan sekitarnya",
        "district": "Kedamaian",
        "subdistrict": "Kedamaian",
        "source_type": "admin_input",
        "source_reference": "Dataset simulasi pengembangan SIGAP Banjir; lokasi area diverifikasi melalui peta publik OpenStreetMap/Nominatim, tingkat risiko merupakan skenario uji aplikasi.",
        "is_verified": false,
        "data_status": "simulasi",
        "longitude": 105.2816,
        "latitude": -5.4095,
        "dataset": "flood_risk_points"
    },
    {
        "id": 19,
        "name": "Rawan Banjir Labuhan Ratu",
        "address": "Area Labuhan Ratu Raya",
        "district": "Labuhan Ratu",
        "subdistrict": "Labuhan Ratu Raya",
        "source_type": "admin_input",
        "source_reference": "Dataset simulasi pengembangan SIGAP Banjir; lokasi area diverifikasi melalui peta publik OpenStreetMap/Nominatim, tingkat risiko merupakan skenario uji aplikasi.",
        "is_verified": false,
        "data_status": "simulasi",
        "longitude": 105.2448,
        "latitude": -5.3756,
        "dataset": "flood_risk_points"
    },
    {
        "id": 20,
        "name": "Rawan Banjir Tanjung Karang Timur",
        "address": "Koridor jalan permukiman Tanjung Karang Timur",
        "district": "Tanjung Karang Timur",
        "subdistrict": "Kota Baru",
        "source_type": "admin_input",
        "source_reference": "Dataset simulasi pengembangan SIGAP Banjir; lokasi area diverifikasi melalui peta publik OpenStreetMap/Nominatim, tingkat risiko merupakan skenario uji aplikasi.",
        "is_verified": false,
        "data_status": "simulasi",
        "longitude": 105.2779,
        "latitude": -5.4163,
        "dataset": "flood_risk_points"
    },
    {
        "id": 21,
        "name": "Rawan Banjir Bumi Waras",
        "address": "Area Bumi Waras dekat pesisir",
        "district": "Bumi Waras",
        "subdistrict": "Bumi Waras",
        "source_type": "admin_input",
        "source_reference": "Dataset simulasi pengembangan SIGAP Banjir; lokasi area diverifikasi melalui peta publik OpenStreetMap/Nominatim, tingkat risiko merupakan skenario uji aplikasi.",
        "is_verified": false,
        "data_status": "simulasi",
        "longitude": 105.2701,
        "latitude": -5.4364,
        "dataset": "flood_risk_points"
    },
    {
        "id": 22,
        "name": "Rawan Banjir Enggal",
        "address": "Area pusat kota Enggal",
        "district": "Enggal",
        "subdistrict": "Enggal",
        "source_type": "admin_input",
        "source_reference": "Dataset simulasi pengembangan SIGAP Banjir; lokasi area diverifikasi melalui peta publik OpenStreetMap/Nominatim, tingkat risiko merupakan skenario uji aplikasi.",
        "is_verified": false,
        "data_status": "simulasi",
        "longitude": 105.2597,
        "latitude": -5.4189,
        "dataset": "flood_risk_points"
    },
    {
        "id": 23,
        "name": "Rawan Banjir Kemiling Permai",
        "address": "Permukiman Kemiling Permai",
        "district": "Kemiling",
        "subdistrict": "Kemiling Permai",
        "source_type": "admin_input",
        "source_reference": "Dataset simulasi pengembangan SIGAP Banjir; lokasi area diverifikasi melalui peta publik OpenStreetMap/Nominatim, tingkat risiko merupakan skenario uji aplikasi.",
        "is_verified": false,
        "data_status": "simulasi",
        "longitude": 105.2149,
        "latitude": -5.397,
        "dataset": "flood_risk_points"
    },
    {
        "id": 24,
        "name": "Rawan Banjir Teluk Betung Timur",
        "address": "Koridor akses Teluk Betung Timur",
        "district": "Teluk Betung Timur",
        "subdistrict": "Keteguhan",
        "source_type": "admin_input",
        "source_reference": "Dataset simulasi pengembangan SIGAP Banjir; lokasi area diverifikasi melalui peta publik OpenStreetMap/Nominatim, tingkat risiko merupakan skenario uji aplikasi.",
        "is_verified": false,
        "data_status": "simulasi",
        "longitude": 105.2787,
        "latitude": -5.4555,
        "dataset": "flood_risk_points"
    },
    {
        "id": 11,
        "name": "Masjid Al-Furqon Lungsir",
        "address": "Area Lungsir, Tanjung Karang Pusat",
        "district": "Tanjung Karang Pusat",
        "subdistrict": "Lungsir",
        "source_type": "admin_input",
        "source_reference": "Dataset simulasi pengembangan SIGAP Banjir; lokasi fasilitas/area diverifikasi melalui peta publik OpenStreetMap/Nominatim, fungsi evakuasi merupakan skenario uji aplikasi.",
        "is_verified": false,
        "data_status": "simulasi",
        "longitude": 105.2635,
        "latitude": -5.423,
        "dataset": "evacuation_points"
    },
    {
        "id": 12,
        "name": "GOR Saburai",
        "address": "Kompleks GOR Saburai, Enggal",
        "district": "Enggal",
        "subdistrict": "Enggal",
        "source_type": "admin_input",
        "source_reference": "Dataset simulasi pengembangan SIGAP Banjir; lokasi fasilitas/area diverifikasi melalui peta publik OpenStreetMap/Nominatim, fungsi evakuasi merupakan skenario uji aplikasi.",
        "is_verified": false,
        "data_status": "simulasi",
        "longitude": 105.2598,
        "latitude": -5.4218,
        "dataset": "evacuation_points"
    },
    {
        "id": 13,
        "name": "Kantor Kecamatan Teluk Betung Selatan",
        "address": "Area kantor kecamatan Teluk Betung Selatan",
        "district": "Teluk Betung Selatan",
        "subdistrict": "Pesawahan",
        "source_type": "admin_input",
        "source_reference": "Dataset simulasi pengembangan SIGAP Banjir; lokasi fasilitas/area diverifikasi melalui peta publik OpenStreetMap/Nominatim, fungsi evakuasi merupakan skenario uji aplikasi.",
        "is_verified": false,
        "data_status": "simulasi",
        "longitude": 105.2591,
        "latitude": -5.4485,
        "dataset": "evacuation_points"
    },
    {
        "id": 14,
        "name": "Aula Kecamatan Panjang",
        "address": "Area Kecamatan Panjang",
        "district": "Panjang",
        "subdistrict": "Panjang Utara",
        "source_type": "admin_input",
        "source_reference": "Dataset simulasi pengembangan SIGAP Banjir; lokasi fasilitas/area diverifikasi melalui peta publik OpenStreetMap/Nominatim, fungsi evakuasi merupakan skenario uji aplikasi.",
        "is_verified": false,
        "data_status": "simulasi",
        "longitude": 105.3314,
        "latitude": -5.4682,
        "dataset": "evacuation_points"
    },
    {
        "id": 15,
        "name": "Puskesmas Sukarame",
        "address": "Area layanan kesehatan Sukarame",
        "district": "Sukarame",
        "subdistrict": "Sukarame Baru",
        "source_type": "admin_input",
        "source_reference": "Dataset simulasi pengembangan SIGAP Banjir; lokasi fasilitas/area diverifikasi melalui peta publik OpenStreetMap/Nominatim, fungsi evakuasi merupakan skenario uji aplikasi.",
        "is_verified": false,
        "data_status": "simulasi",
        "longitude": 105.3025,
        "latitude": -5.3775,
        "dataset": "evacuation_points"
    },
    {
        "id": 16,
        "name": "SDN Simulasi Way Halim",
        "address": "Area sekolah Way Halim Permai",
        "district": "Way Halim",
        "subdistrict": "Way Halim Permai",
        "source_type": "admin_input",
        "source_reference": "Dataset simulasi pengembangan SIGAP Banjir; lokasi fasilitas/area diverifikasi melalui peta publik OpenStreetMap/Nominatim, fungsi evakuasi merupakan skenario uji aplikasi.",
        "is_verified": false,
        "data_status": "simulasi",
        "longitude": 105.2878,
        "latitude": -5.389,
        "dataset": "evacuation_points"
    },
    {
        "id": 17,
        "name": "Lapangan Enggal",
        "address": "Area lapangan terbuka Enggal",
        "district": "Enggal",
        "subdistrict": "Enggal",
        "source_type": "admin_input",
        "source_reference": "Dataset simulasi pengembangan SIGAP Banjir; lokasi fasilitas/area diverifikasi melalui peta publik OpenStreetMap/Nominatim, fungsi evakuasi merupakan skenario uji aplikasi.",
        "is_verified": false,
        "data_status": "simulasi",
        "longitude": 105.2593,
        "latitude": -5.4175,
        "dataset": "evacuation_points"
    },
    {
        "id": 18,
        "name": "Balai Warga Rajabasa Nunyai",
        "address": "Area Rajabasa Nunyai",
        "district": "Rajabasa",
        "subdistrict": "Rajabasa Nunyai",
        "source_type": "admin_input",
        "source_reference": "Dataset simulasi pengembangan SIGAP Banjir; lokasi fasilitas/area diverifikasi melalui peta publik OpenStreetMap/Nominatim, fungsi evakuasi merupakan skenario uji aplikasi.",
        "is_verified": false,
        "data_status": "simulasi",
        "longitude": 105.2299,
        "latitude": -5.371,
        "dataset": "evacuation_points"
    },
    {
        "id": 19,
        "name": "Masjid Simulasi Kemiling",
        "address": "Area Kemiling Permai",
        "district": "Kemiling",
        "subdistrict": "Kemiling Permai",
        "source_type": "admin_input",
        "source_reference": "Dataset simulasi pengembangan SIGAP Banjir; lokasi fasilitas/area diverifikasi melalui peta publik OpenStreetMap/Nominatim, fungsi evakuasi merupakan skenario uji aplikasi.",
        "is_verified": false,
        "data_status": "simulasi",
        "longitude": 105.2157,
        "latitude": -5.3971,
        "dataset": "evacuation_points"
    },
    {
        "id": 20,
        "name": "Balai Warga Kedamaian",
        "address": "Area Balai Warga Kedamaian",
        "district": "Kedamaian",
        "subdistrict": "Kedamaian",
        "source_type": "admin_input",
        "source_reference": "Dataset simulasi pengembangan SIGAP Banjir; lokasi fasilitas/area diverifikasi melalui peta publik OpenStreetMap/Nominatim, fungsi evakuasi merupakan skenario uji aplikasi.",
        "is_verified": false,
        "data_status": "simulasi",
        "longitude": 105.2815,
        "latitude": -5.41,
        "dataset": "evacuation_points"
    },
    {
        "id": 7,
        "name": "Pos Alat Berat Panjang",
        "address": "Area operasional sekitar Pelabuhan Panjang",
        "district": "Panjang",
        "subdistrict": "Panjang Utara",
        "source_type": "dummy",
        "source_reference": "Dataset dummy pengembangan SIGAP Banjir; lokasi area pos berbasis wilayah Bandar Lampung dan diverifikasi melalui peta publik OpenStreetMap/Nominatim, bukan fasilitas resmi.",
        "is_verified": false,
        "data_status": "dummy",
        "longitude": 105.3262,
        "latitude": -5.4669,
        "dataset": "heavy_equipment_posts"
    },
    {
        "id": 8,
        "name": "Pos Alat Berat Teluk Betung",
        "address": "Area operasional Teluk Betung Selatan",
        "district": "Teluk Betung Selatan",
        "subdistrict": "Pesawahan",
        "source_type": "dummy",
        "source_reference": "Dataset dummy pengembangan SIGAP Banjir; lokasi area pos berbasis wilayah Bandar Lampung dan diverifikasi melalui peta publik OpenStreetMap/Nominatim, bukan fasilitas resmi.",
        "is_verified": false,
        "data_status": "dummy",
        "longitude": 105.259,
        "latitude": -5.4442,
        "dataset": "heavy_equipment_posts"
    },
    {
        "id": 9,
        "name": "Pos Alat Berat Rajabasa",
        "address": "Area operasional sekitar Rajabasa Nunyai",
        "district": "Rajabasa",
        "subdistrict": "Rajabasa Nunyai",
        "source_type": "dummy",
        "source_reference": "Dataset dummy pengembangan SIGAP Banjir; lokasi area pos berbasis wilayah Bandar Lampung dan diverifikasi melalui peta publik OpenStreetMap/Nominatim, bukan fasilitas resmi.",
        "is_verified": false,
        "data_status": "dummy",
        "longitude": 105.229,
        "latitude": -5.3729,
        "dataset": "heavy_equipment_posts"
    },
    {
        "id": 10,
        "name": "Pos Alat Berat Way Halim",
        "address": "Area operasional Way Halim Permai",
        "district": "Way Halim",
        "subdistrict": "Way Halim Permai",
        "source_type": "dummy",
        "source_reference": "Dataset dummy pengembangan SIGAP Banjir; lokasi area pos berbasis wilayah Bandar Lampung dan diverifikasi melalui peta publik OpenStreetMap/Nominatim, bukan fasilitas resmi.",
        "is_verified": false,
        "data_status": "dummy",
        "longitude": 105.2896,
        "latitude": -5.3912,
        "dataset": "heavy_equipment_posts"
    },
    {
        "id": 11,
        "name": "Pos Alat Berat Sukarame",
        "address": "Area operasional sekitar Korpri Sukarame",
        "district": "Sukarame",
        "subdistrict": "Korpri Raya",
        "source_type": "dummy",
        "source_reference": "Dataset dummy pengembangan SIGAP Banjir; lokasi area pos berbasis wilayah Bandar Lampung dan diverifikasi melalui peta publik OpenStreetMap/Nominatim, bukan fasilitas resmi.",
        "is_verified": false,
        "data_status": "dummy",
        "longitude": 105.3068,
        "latitude": -5.3812,
        "dataset": "heavy_equipment_posts"
    },
    {
        "id": 12,
        "name": "Pos Alat Berat Kemiling",
        "address": "Area operasional Kemiling Permai",
        "district": "Kemiling",
        "subdistrict": "Kemiling Permai",
        "source_type": "dummy",
        "source_reference": "Dataset dummy pengembangan SIGAP Banjir; lokasi area pos berbasis wilayah Bandar Lampung dan diverifikasi melalui peta publik OpenStreetMap/Nominatim, bukan fasilitas resmi.",
        "is_verified": false,
        "data_status": "dummy",
        "longitude": 105.214,
        "latitude": -5.3965,
        "dataset": "heavy_equipment_posts"
    }
]